omnibase_core/__init__.py
omnibase_core/__init___fast.py
omnibase_core/constants/__init__.py
omnibase_core/constants/constants_contract_fields.py
omnibase_core/constants/event_types.py
omnibase_core/container/__init__.py
omnibase_core/container/container_service_resolver.py
omnibase_core/container/service_registry.py
omnibase_core/data/config/mixin_metadata.yaml
omnibase_core/decorators/__init__.py
omnibase_core/decorators/decorator_allow_any_type.py
omnibase_core/decorators/error_handling.py
omnibase_core/decorators/pattern_exclusions.py
omnibase_core/discovery/__init__.py
omnibase_core/enums/__init__.py
omnibase_core/enums/enum_acknowledgment_type.py
omnibase_core/enums/enum_action_category.py
omnibase_core/enums/enum_agent_capability.py
omnibase_core/enums/enum_agent_status_type.py
omnibase_core/enums/enum_analysis_status.py
omnibase_core/enums/enum_architecture.py
omnibase_core/enums/enum_argument_type.py
omnibase_core/enums/enum_artifact_type.py
omnibase_core/enums/enum_assembly_strategy.py
omnibase_core/enums/enum_audit_action.py
omnibase_core/enums/enum_auth_type.py
omnibase_core/enums/enum_authentication_method.py
omnibase_core/enums/enum_backend_type.py
omnibase_core/enums/enum_backoff_strategy.py
omnibase_core/enums/enum_base_status.py
omnibase_core/enums/enum_business_logic_pattern.py
omnibase_core/enums/enum_cache_eviction_policy.py
omnibase_core/enums/enum_case_style.py
omnibase_core/enums/enum_category.py
omnibase_core/enums/enum_category_filter.py
omnibase_core/enums/enum_cell_type.py
omnibase_core/enums/enum_chain_validation_status.py
omnibase_core/enums/enum_checkpoint_status.py
omnibase_core/enums/enum_checkpoint_type.py
omnibase_core/enums/enum_circuit_breaker_state.py
omnibase_core/enums/enum_cli_action.py
omnibase_core/enums/enum_cli_context_value_type.py
omnibase_core/enums/enum_cli_discovery_action.py
omnibase_core/enums/enum_cli_exit_code.py
omnibase_core/enums/enum_cli_input_value_type.py
omnibase_core/enums/enum_cli_option_value_type.py
omnibase_core-0.3.2.dist-info/METADATA
omnibase_core-0.3.2.dist-info/WHEEL
omnibase_core-0.3.2.dist-info/entry_points.txt
omnibase_core-0.3.2.dist-info/licenses/LICENSE
omnibase_core-0.3.2.dist-info/RECORD
