Metadata-Version: 2.4
Name: omnibase_core
Version: 0.3.2
Summary: ONEX Core Framework - Base classes and essential implementations
License-Expression: MIT
License-File: LICENSE
Keywords: onex,framework,architecture,dependency-injection,base-classes,infrastructure,event-driven,error-handling,node-architecture
Author: OmniNode Team
Author-email: team@omninode.ai
Requires-Python: >=3.12
Classifier: Development Status :: 4 - Beta
Classifier: Intended Audience :: Developers
Classifier: Programming Language :: Python :: 3.12
Classifier: Programming Language :: Python :: 3 :: Only
Classifier: Topic :: Software Development :: Libraries :: Application Frameworks
Classifier: Topic :: Software Development :: Libraries :: Python Modules
Classifier: Typing :: Typed
Provides-Extra: cli
Provides-Extra: full
Requires-Dist: aiohttp (>=3.9.0,<4.0.0)
Requires-Dist: asyncpg (>=0.29.0,<0.30.0)
Requires-Dist: click (>=8.1.0,<9.0.0)
Requires-Dist: dependency-injector (>=4.48.1,<5.0.0)
Requires-Dist: fastapi (>=0.120.1,<0.121.0)
Requires-Dist: llama-index (>=0.14.0,<0.15.0)
Requires-Dist: omnibase-spi (>=0.2.0,<0.3.0)
Requires-Dist: psutil ; extra == "cli"
Requires-Dist: psutil ; extra == "full"
Requires-Dist: psycopg2-binary (>=2.9.10,<3.0.0)
Requires-Dist: pydantic (>=2.11.7,<3.0.0)
Requires-Dist: pypdf (>=6.1.0,<7.0.0)
Requires-Dist: python-consul (>=1.1.0,<2.0.0)
Requires-Dist: pyyaml (>=6.0.2,<7.0.0)
Requires-Dist: redis (>=6.4.0,<7.0.0)
Requires-Dist: rich (>=13.7.0,<14.0.0)
Requires-Dist: starlette (>=0.49.1,<0.50.0)
Requires-Dist: uvicorn (>=0.32.0,<0.33.0)
Project-URL: Documentation, https://github.com/OmniNode-ai/omnibase_core/tree/main/docs
Project-URL: Homepage, https://github.com/OmniNode-ai/omnibase_core
Project-URL: Repository, https://github.com/OmniNode-ai/omnibase_core
